ruffly/__init__.py
ruffly/cli.py
ruffly/default.toml
ruffly-0.0.3.dist-info/LICENSE
ruffly-0.0.3.dist-info/METADATA
ruffly-0.0.3.dist-info/WHEEL
ruffly-0.0.3.dist-info/entry_points.txt
ruffly-0.0.3.dist-info/top_level.txt
ruffly-0.0.3.dist-info/RECORD
